c11_log_lib/__init__.py
c11_log_lib/logger.py
lib/__init__.py
lib/logger.py
c11_log_lib-0.1.6.dist-info/METADATA
c11_log_lib-0.1.6.dist-info/WHEEL
c11_log_lib-0.1.6.dist-info/top_level.txt
c11_log_lib-0.1.6.dist-info/RECORD
