Metadata-Version: 2.1
Name: c11-log-lib
Version: 0.1.6
Summary: A structured logging library for Python
Home-page: https://github.com/code11/python-log
Author: C11
Classifier: Programming Language :: Python :: 3
Classifier: License :: OSI Approved :: MIT License
Classifier: Operating System :: OS Independent
Requires-Python: >=3.6
Requires-Dist: structlog
